LICENSE
bap/__init__.py
lunar/__init__.py
lunar/cli.py
lunar/config/__init__.py
lunar/data/__init__.py
lunar/data/batch/__init__.py
lunar/data/batch/batch.py
lunar/data/batch/models/__init__.py
lunar/data/batch/models/batch_models.py
lunar/data/data/__init__.py
lunar/data/data/data.py
lunar/data/datasets/__init__.py
lunar/data/datasets/dataset.py
lunar/data/datasets/models/__init__.py
lunar/data/datasets/models/dataset_models.py
lunar/data/datasets/models/params/__init__.py
lunar/data/datasets/models/params/dynamodb.py
lunar/data/dynamodb/__init__.py
lunar/data/dynamodb/dynamodb.py
lunar/data/query/__init__.py
lunar/data/query/query.py
lunar/lunar_client.py
lunar/ml/__init__.py
lunar/ml/aidp_service.py
lunar/ml/edd_service.py
lunar/ml/lunar_model.py
lunar/ml/model_registry.py
lunar/rec/__init__.py
lunar/rec/channels/__init__.py
lunar/rec/channels/channel.py
lunar/rec/channels/models/__init__.py
lunar/rec/channels/models/channel_models.py
lunar/rec/experiments/__init__.py
lunar/rec/experiments/experiment.py
lunar/rec/experiments/models/__init__.py
lunar/rec/experiments/models/experiment_models.py
lunar/rec/recommendations/__init__.py
lunar/rec/recommendations/models/__init__.py
lunar/rec/recommendations/models/recommendation_models.py
lunar/rec/recommendations/recommendation.py
apollo_lunar-2024.5.21.dist-info/LICENSE
apollo_lunar-2024.5.21.dist-info/METADATA
apollo_lunar-2024.5.21.dist-info/WHEEL
apollo_lunar-2024.5.21.dist-info/entry_points.txt
apollo_lunar-2024.5.21.dist-info/RECORD
