Metadata-Version: 2.1
Name: apollo-lunar
Version: 2024.5.21
Summary: A Python SDK/CLI for Lunar API
License: MIT
Author: Lunar module
Author-email: lunar@sktio.io
Requires-Python: >=3.10,<4.0
Classifier: License :: OSI Approved :: MIT License
Classifier: Programming Language :: Python :: 3
Classifier: Programming Language :: Python :: 3.10
Classifier: Programming Language :: Python :: 3.11
Classifier: Programming Language :: Python :: 3.12
Provides-Extra: ml
Provides-Extra: skt
Requires-Dist: aiohttp (>=3.8.1,<4.0.0)
Requires-Dist: boto3
Requires-Dist: catboost (>=1.0.6,<1.1.0) ; extra == "ml"
Requires-Dist: click (>=8.1.2,<9.0.0)
Requires-Dist: cloudpickle (>=2.1.0,<3.0.0)
Requires-Dist: lightgbm (>=3.3.2,<3.4.0) ; extra == "ml"
Requires-Dist: opensearch-py (>=2.3.1,<3.0.0)
Requires-Dist: pydantic (>=1.8.2,<2.0.0)
Requires-Dist: requests (>=2.27.1,<3.0.0)
Requires-Dist: scikit-learn (>=1.1.1,<1.2.0) ; extra == "ml"
Requires-Dist: xgboost (>=1.6.1,<1.7.0) ; extra == "ml"
